constclasses/__init__.py
constclasses/ccerror.py
constclasses/const_class.py
constclasses/const_class_base.py
constclasses/static_const_class.py
pyconstclasses-1.0.5.dist-info/LICENSE
pyconstclasses-1.0.5.dist-info/METADATA
pyconstclasses-1.0.5.dist-info/WHEEL
pyconstclasses-1.0.5.dist-info/top_level.txt
pyconstclasses-1.0.5.dist-info/RECORD
