Metadata-Version: 2.1
Name: pyconstclasses
Version: 1.0.5
Summary: Package with const class decoratos and utility
Author: SpectraL519
License: MIT License
Project-URL: Repository, https://github.com/SpectraL519/pyconstclasses.git
Keywords: const,const class,const classes
Classifier: Development Status :: 5 - Production/Stable
Classifier: Intended Audience :: Developers
Classifier: Topic :: Software Development :: Libraries :: Python Modules
Classifier: License :: OSI Approved :: MIT License
Classifier: Programming Language :: Python :: 3
Classifier: Programming Language :: Python :: 3.9
Classifier: Programming Language :: Python :: 3.10
Classifier: Programming Language :: Python :: 3.11
Classifier: Programming Language :: Python :: 3.12
Requires-Python: >=3.9
License-File: LICENSE
Provides-Extra: dev
Provides-Extra: test
Requires-Dist: tox ; extra == 'test'
